brisk/Request.py
brisk/Response.py
brisk/__init__.py
brisk/main.py
brisk/mime.py
brisk/render.py
Brisk_py-0.2.0.dist-info/LICENSE
Brisk_py-0.2.0.dist-info/METADATA
Brisk_py-0.2.0.dist-info/WHEEL
Brisk_py-0.2.0.dist-info/top_level.txt
Brisk_py-0.2.0.dist-info/RECORD
