Metadata-Version: 2.1
Name: Brisk-py
Version: 0.2.0
Summary: A way to create a lightning fast HTTP server using ASGI
Home-page: https://github.com/briskpy/brisk
Author: Reet Singh
Author-email: reet22singh+brisk@gmail.com
License: UNKNOWN
Project-URL: Bug Tracker, https://github.com/briskpy/brisk/issues
Project-URL: Documentation, https://github.com/briskpy/brisk
Platform: UNKNOWN
Classifier: Development Status :: 2 - Pre-Alpha
Classifier: Environment :: Web Environment
Classifier: Intended Audience :: Developers
Classifier: Programming Language :: Python :: 3 :: Only
Classifier: Programming Language :: Python :: 3.7
Classifier: Programming Language :: Python :: 3.8
Classifier: Programming Language :: Python :: 3.9
Classifier: License :: OSI Approved :: MIT License
Classifier: Operating System :: OS Independent
Classifier: Topic :: Internet :: WWW/HTTP
Classifier: Topic :: Internet :: WWW/HTTP :: Dynamic Content
Classifier: Topic :: Internet :: WWW/HTTP :: HTTP Servers
Classifier: Topic :: Internet :: WWW/HTTP :: WSGI
Classifier: Topic :: Software Development :: Libraries :: Application Frameworks
Classifier: Topic :: Software Development :: Libraries :: Python Modules
Requires-Python: >=3.7
License-File: LICENSE
